fluidly_structlog-0.1.8-py3.7-nspkg.pth
fluidly/structlog/__init__.py
fluidly/structlog/base_logger.py
fluidly/structlog/pubsub_helper.py
fluidly/structlog/py.typed
fluidly/structlog/timing.py
fluidly_structlog-0.1.8.dist-info/METADATA
fluidly_structlog-0.1.8.dist-info/WHEEL
fluidly_structlog-0.1.8.dist-info/namespace_packages.txt
fluidly_structlog-0.1.8.dist-info/top_level.txt
fluidly_structlog-0.1.8.dist-info/RECORD
